{
  "file": "core/src/ptr/non_null.rs",
  "name": "ptr::non_null::NonNull::<i16>::add",
  "hash": "1166494283876212099134096179892720893",
  "hash_direct": "31469174662678929578840776536833083710",
  "src": "pub const unsafe fn add(self, count: usize) -> Self\n    where\n        T: Sized,\n    {\n        // SAFETY: the caller must uphold the safety contract for `offset`.\n        // Additionally safety contract of `offset` guarantees that the resulting pointer is\n        // pointing to an allocation, there can't be an allocation at null, thus it's safe to\n        // construct `NonNull`.\n        unsafe { NonNull { pointer: intrinsics::offset(self.as_ptr(), count) } }\n    }",
  "callees": [
    "803219541133870099912353139964899648466"
  ]
}
