{
  "file": "core/src/intrinsics/mod.rs",
  "name": "core::ub_checks::maybe_is_nonoverlapping::runtime",
  "hash": "489523557192025460313854164093687544855",
  "hash_direct": "99384550020006566015058015950789611572",
  "src": "fn runtime$(<$($binders)*>)?($($arg: $ty),*) $( -> $ret )? {\n            $runtime\n        }",
  "macro_backtrace": [
    {
      "callsite": "$crate::intrinsics::const_eval_select!(\n            @capture$([$($binders)*])? { $($arg : $ty = $val),* } $(-> $ret)? :\n            #[noinline]\n            if const\n                #[inline] // prevent codegen on this function\n                $(#[$compiletime_attr])*\n                $compiletime\n            else\n                #[inline] // avoid the overhead of an extra fn call\n                $(#[$runtime_attr])*\n                $runtime\n        )",
      "defsite": "pub(crate) macro const_eval_select {\n    (\n        @capture$([$($binders:tt)*])? { $($arg:ident : $ty:ty = $val:expr),* $(,)? } $( -> $ret:ty )? :\n        if const\n            $(#[$compiletime_attr:meta])* $compiletime:block\n        else\n            $(#[$runtime_attr:meta])* $runtime:block\n    ) => {\n        // Use the `noinline` arm, after adding explicit `inline` attributes\n        $crate::intrinsics::const_eval_select!(\n            @capture$([$($binders)*])? { $($arg : $ty = $val),* } $(-> $ret)? :\n            #[noinline]\n            if const\n                #[inline] // prevent codegen on this function\n                $(#[$compiletime_attr])*\n                $compiletime\n            else\n                #[inline] // avoid the overhead of an extra fn call\n                $(#[$runtime_attr])*\n                $runtime\n        )\n    },\n    // With a leading #[noinline], we don't add inline attributes\n    (\n        @capture$([$($binders:tt)*])? { $($arg:ident : $ty:ty = $val:expr),* $(,)? } $( -> $ret:ty )? :\n        #[noinline]\n        if const\n            $(#[$compiletime_attr:meta])* $compiletime:block\n        else\n            $(#[$runtime_attr:meta])* $runtime:block\n    ) => {{\n        $(#[$runtime_attr])*\n        fn runtime$(<$($binders)*>)?($($arg: $ty),*) $( -> $ret )? {\n            $runtime\n        }\n\n        $(#[$compiletime_attr])*\n        const fn compiletime$(<$($binders)*>)?($($arg: $ty),*) $( -> $ret )? {\n            // Don't warn if one of the arguments is unused.\n            $(let _ = $arg;)*\n\n            $compiletime\n        }\n\n        const_eval_select(($($val,)*), compiletime, runtime)\n    }},\n    // We support leaving away the `val` expressions for *all* arguments\n    // (but not for *some* arguments, that's too tricky).\n    (\n        @capture$([$($binders:tt)*])? { $($arg:ident : $ty:ty),* $(,)? } $( -> $ret:ty )? :\n        if const\n            $(#[$compiletime_attr:meta])* $compiletime:block\n        else\n            $(#[$runtime_attr:meta])* $runtime:block\n    ) => {\n        $crate::intrinsics::const_eval_select!(\n            @capture$([$($binders)*])? { $($arg : $ty = $arg),* } $(-> $ret)? :\n            if const\n                $(#[$compiletime_attr])* $compiletime\n            else\n                $(#[$runtime_attr])* $runtime\n        )\n    },\n}"
    },
    {
      "callsite": "$crate::intrinsics::const_eval_select!(\n            @capture$([$($binders)*])? { $($arg : $ty = $arg),* } $(-> $ret)? :\n            if const\n                $(#[$compiletime_attr])* $compiletime\n            else\n                $(#[$runtime_attr])* $runtime\n        )",
      "defsite": "pub(crate) macro const_eval_select {\n    (\n        @capture$([$($binders:tt)*])? { $($arg:ident : $ty:ty = $val:expr),* $(,)? } $( -> $ret:ty )? :\n        if const\n            $(#[$compiletime_attr:meta])* $compiletime:block\n        else\n            $(#[$runtime_attr:meta])* $runtime:block\n    ) => {\n        // Use the `noinline` arm, after adding explicit `inline` attributes\n        $crate::intrinsics::const_eval_select!(\n            @capture$([$($binders)*])? { $($arg : $ty = $val),* } $(-> $ret)? :\n            #[noinline]\n            if const\n                #[inline] // prevent codegen on this function\n                $(#[$compiletime_attr])*\n                $compiletime\n            else\n                #[inline] // avoid the overhead of an extra fn call\n                $(#[$runtime_attr])*\n                $runtime\n        )\n    },\n    // With a leading #[noinline], we don't add inline attributes\n    (\n        @capture$([$($binders:tt)*])? { $($arg:ident : $ty:ty = $val:expr),* $(,)? } $( -> $ret:ty )? :\n        #[noinline]\n        if const\n            $(#[$compiletime_attr:meta])* $compiletime:block\n        else\n            $(#[$runtime_attr:meta])* $runtime:block\n    ) => {{\n        $(#[$runtime_attr])*\n        fn runtime$(<$($binders)*>)?($($arg: $ty),*) $( -> $ret )? {\n            $runtime\n        }\n\n        $(#[$compiletime_attr])*\n        const fn compiletime$(<$($binders)*>)?($($arg: $ty),*) $( -> $ret )? {\n            // Don't warn if one of the arguments is unused.\n            $(let _ = $arg;)*\n\n            $compiletime\n        }\n\n        const_eval_select(($($val,)*), compiletime, runtime)\n    }},\n    // We support leaving away the `val` expressions for *all* arguments\n    // (but not for *some* arguments, that's too tricky).\n    (\n        @capture$([$($binders:tt)*])? { $($arg:ident : $ty:ty),* $(,)? } $( -> $ret:ty )? :\n        if const\n            $(#[$compiletime_attr:meta])* $compiletime:block\n        else\n            $(#[$runtime_attr:meta])* $runtime:block\n    ) => {\n        $crate::intrinsics::const_eval_select!(\n            @capture$([$($binders)*])? { $($arg : $ty = $arg),* } $(-> $ret)? :\n            if const\n                $(#[$compiletime_attr])* $compiletime\n            else\n                $(#[$runtime_attr])* $runtime\n        )\n    },\n}"
    },
    {
      "callsite": "const_eval_select!(\n        @capture { src: *const (), dst: *const (), size: usize, count: usize } -> bool:\n        if const {\n            true\n        } else {\n            let src_usize = src.addr();\n            let dst_usize = dst.addr();\n            let Some(size) = size.checked_mul(count) else {\n                crate::panicking::panic_nounwind(\n                    \"is_nonoverlapping: `size_of::<T>() * count` overflows a usize\",\n                )\n            };\n            let diff = src_usize.abs_diff(dst_usize);\n            // If the absolute distance between the ptrs is at least as big as the size of the buffer,\n            // they do not overlap.\n            diff >= size\n        }\n    )",
      "defsite": "pub(crate) macro const_eval_select {\n    (\n        @capture$([$($binders:tt)*])? { $($arg:ident : $ty:ty = $val:expr),* $(,)? } $( -> $ret:ty )? :\n        if const\n            $(#[$compiletime_attr:meta])* $compiletime:block\n        else\n            $(#[$runtime_attr:meta])* $runtime:block\n    ) => {\n        // Use the `noinline` arm, after adding explicit `inline` attributes\n        $crate::intrinsics::const_eval_select!(\n            @capture$([$($binders)*])? { $($arg : $ty = $val),* } $(-> $ret)? :\n            #[noinline]\n            if const\n                #[inline] // prevent codegen on this function\n                $(#[$compiletime_attr])*\n                $compiletime\n            else\n                #[inline] // avoid the overhead of an extra fn call\n                $(#[$runtime_attr])*\n                $runtime\n        )\n    },\n    // With a leading #[noinline], we don't add inline attributes\n    (\n        @capture$([$($binders:tt)*])? { $($arg:ident : $ty:ty = $val:expr),* $(,)? } $( -> $ret:ty )? :\n        #[noinline]\n        if const\n            $(#[$compiletime_attr:meta])* $compiletime:block\n        else\n            $(#[$runtime_attr:meta])* $runtime:block\n    ) => {{\n        $(#[$runtime_attr])*\n        fn runtime$(<$($binders)*>)?($($arg: $ty),*) $( -> $ret )? {\n            $runtime\n        }\n\n        $(#[$compiletime_attr])*\n        const fn compiletime$(<$($binders)*>)?($($arg: $ty),*) $( -> $ret )? {\n            // Don't warn if one of the arguments is unused.\n            $(let _ = $arg;)*\n\n            $compiletime\n        }\n\n        const_eval_select(($($val,)*), compiletime, runtime)\n    }},\n    // We support leaving away the `val` expressions for *all* arguments\n    // (but not for *some* arguments, that's too tricky).\n    (\n        @capture$([$($binders:tt)*])? { $($arg:ident : $ty:ty),* $(,)? } $( -> $ret:ty )? :\n        if const\n            $(#[$compiletime_attr:meta])* $compiletime:block\n        else\n            $(#[$runtime_attr:meta])* $runtime:block\n    ) => {\n        $crate::intrinsics::const_eval_select!(\n            @capture$([$($binders)*])? { $($arg : $ty = $arg),* } $(-> $ret)? :\n            if const\n                $(#[$compiletime_attr])* $compiletime\n            else\n                $(#[$runtime_attr])* $runtime\n        )\n    },\n}"
    }
  ],
  "callees": [
    "12281449246394340237926324936375242532",
    "99835071136844477394667148890151411684",
    "73694171442177138896992135977130617471",
    "181267529910573756716102767087485333561",
    "149201007125728463455320865149411692001",
    "50732326018270804158617132727999669219",
    "280432584315771372815037115035770855991",
    "112886468787774265616636362149708028018",
    "62127822181510782405608732116999447182",
    "1578257332020894271617658554056373986878",
    "896899668436043458214649410678042895693",
    "17976542625295060605041426324269334020",
    "8010637041282557608011263416999007001",
    "986792852990965178117440249555081278778",
    "90818112465881722349174357944217011292",
    "1357412281760869556115161719233556173642",
    "63085389524472853348886374617170044294",
    "175623961004431005849298709567805707658",
    "33067340742295788584221598515845050786"
  ]
}
