{
  "file": "/home/runner/work/distributed-verification/distributed-verification/kani/library/kani_core/src/mem.rs",
  "name": "kani::mem::has_valid_value::<u8>",
  "hash": "162476659639138462573312662149942342699",
  "hash_direct": "5364335568583302511981166993963009054",
  "attrs": [
    "#[kanitool::fn_marker = \"ValidValueIntrinsic\"]\n"
  ],
  "src": "unsafe fn has_valid_value<T: PointeeSized>(_ptr: *const T) -> bool {\n            kani_intrinsic()\n        }",
  "macro_backtrace": [
    {
      "callsite": "kani_core::kani_mem!(core)",
      "defsite": "macro_rules! kani_mem"
    },
    {
      "callsite": "kani_core::kani_lib!(core)",
      "defsite": "macro_rules! kani_lib"
    }
  ],
  "callees": [
    "1295499066349112484912490938496969975321"
  ]
}
