{
  "file": "/home/runner/work/distributed-verification/distributed-verification/kani/library/kani_core/src/mem.rs",
  "name": "kani::mem::has_valid_value::<[()]>",
  "hash": "74883043860831708044613736828186905895",
  "hash_direct": "1715902805141394281616944222509840026506",
  "attrs": [
    "#[kanitool::fn_marker = \"ValidValueIntrinsic\"]\n"
  ],
  "src": "unsafe fn has_valid_value<T: PointeeSized>(_ptr: *const T) -> bool {\n            kani_intrinsic()\n        }",
  "macro_backtrace": [
    {
      "callsite": "kani_core::kani_mem!(core)",
      "defsite": "macro_rules! kani_mem"
    },
    {
      "callsite": "kani_core::kani_lib!(core)",
      "defsite": "macro_rules! kani_lib"
    }
  ],
  "callees": [
    "22359847832734915742325702083995179865"
  ]
}
