{
  "file": "core/src/fmt/mod.rs",
  "name": "fmt::FormattingOptions::align",
  "hash": "70678707815974353129270849643470718392",
  "hash_direct": "101448442357096109198714534490674056",
  "src": "pub const fn align(&mut self, align: Option<Alignment>) -> &mut Self {\n        let align: u32 = match align {\n            Some(Alignment::Left) => flags::ALIGN_LEFT,\n            Some(Alignment::Right) => flags::ALIGN_RIGHT,\n            Some(Alignment::Center) => flags::ALIGN_CENTER,\n            None => flags::ALIGN_UNKNOWN,\n        };\n        self.flags = self.flags & !flags::ALIGN_BITS | align;\n        self\n    }"
}
