{
  "file": "core/src/result.rs",
  "name": "<core::result::Result<string::String, core::char::DecodeUtf16Error> as core::ops::FromResidual<core::result::Result<core::convert::Infallible, core::char::DecodeUtf16Error>>>::from_residual",
  "hash": "177096721221913413871644018153835656725",
  "hash_direct": "180805316607866702587300977617235909992",
  "src": "fn from_residual(residual: Result<convert::Infallible, E>) -> Self {\n        match residual {\n            Err(e) => Err(From::from(e)),\n        }\n    }",
  "callees": [
    "836386251216121827314945059151032631529"
  ]
}
