{
  "file": "/home/runner/work/distributed-verification/distributed-verification/kani/library/kani_core/src/lib.rs",
  "name": "kani::any_raw::<i32>",
  "hash": "28733051149244335398155852330546270084",
  "hash_direct": "652475687265933189012216527365211447340",
  "attrs": [
    "#[kanitool::fn_marker = \"AnyRawHook\"]\n"
  ],
  "src": "fn any_raw<T: Copy>() -> T {\n            kani_intrinsic()\n        }",
  "macro_backtrace": [
    {
      "callsite": "kani_core::kani_intrinsics!()",
      "defsite": "macro_rules! kani_intrinsics"
    },
    {
      "callsite": "kani_core::kani_lib!(core)",
      "defsite": "macro_rules! kani_lib"
    }
  ],
  "callees": [
    "769871191376860825616640549555308478966"
  ]
}
