{
  "file": "core/src/iter/adapters/flatten.rs",
  "name": "iter::adapters::flatten::FlattenCompat::<option::IntoIter<char::EscapeDebug>, char::EscapeDebug>::new",
  "hash": "147092169516382043437542011004845858622",
  "hash_direct": "1838206629551871287114532450746673719128",
  "src": "fn new(iter: I) -> FlattenCompat<I, U> {\n        FlattenCompat { iter: iter.fuse(), frontiter: None, backiter: None }\n    }",
  "callees": [
    "63841875241618556712129625010832255350",
    "64008405505242811695538648338902736165"
  ]
}
