{
  "file": "/home/runner/work/distributed-verification/distributed-verification/kani/library/kani_core/src/arbitrary/pointer.rs",
  "name": "kani::arbitrary_ptr::PointerGenerator::<12>::any_alloc_status::<(u32, i16, f32)>::{closure#0}",
  "hash": "1003711360985837930312302380480621326588",
  "hash_direct": "1419272170598725567111541061011414930310",
  "src": "|b: &usize| *b < core::mem::size_of::<T>()",
  "macro_backtrace": [
    {
      "callsite": "kani_core::ptr_generator!()",
      "defsite": "macro_rules! ptr_generator"
    },
    {
      "callsite": "kani_core::generate_arbitrary!()",
      "defsite": "macro_rules! generate_arbitrary"
    },
    {
      "callsite": "kani_core::kani_lib!(core)",
      "defsite": "macro_rules! kani_lib"
    }
  ],
  "callees": [
    "627645583140275250012633360066379231959"
  ]
}
