{
  "file": "/home/runner/work/distributed-verification/distributed-verification/kani/library/kani_core/src/arbitrary/pointer.rs",
  "name": "kani::arbitrary_ptr::PointerGenerator::<320>::any_alloc_status::<usize>::{closure#1}",
  "hash": "168916154645668792601125341920594581736",
  "hash_direct": "102857646297764489121195005961614083562",
  "src": "|b: &usize| *b < core::mem::size_of::<T>()",
  "macro_backtrace": [
    {
      "callsite": "kani_core::ptr_generator!()",
      "defsite": "macro_rules! ptr_generator"
    },
    {
      "callsite": "kani_core::generate_arbitrary!()",
      "defsite": "macro_rules! generate_arbitrary"
    },
    {
      "callsite": "kani_core::kani_lib!(core)",
      "defsite": "macro_rules! kani_lib"
    }
  ],
  "callees": [
    "1749362715435459353511933873995340031229"
  ]
}
